playschool_python/__init__.py
playschool_python/__main__.py
playschool_python/cli.py
Playschool_Python-1.0.0.dist-info/AUTHORS.rst
Playschool_Python-1.0.0.dist-info/LICENSE
Playschool_Python-1.0.0.dist-info/METADATA
Playschool_Python-1.0.0.dist-info/NOTICE.py
Playschool_Python-1.0.0.dist-info/WHEEL
Playschool_Python-1.0.0.dist-info/entry_points.txt
Playschool_Python-1.0.0.dist-info/top_level.txt
Playschool_Python-1.0.0.dist-info/RECORD
