Metadata-Version: 2.1
Name: Playschool-Python
Version: 1.0.0
Summary: Python boilerplate short description
Home-page: https://gitlab.yapbreak.fr/olivaa/playschool_python
Author: Adrien Oliva
Author-email: olivaa@yapbreak.fr
License: GNU/GPL v3
Keywords: playschool_python
Platform: UNKNOWN
Classifier: Development Status :: 1 - Planning
Classifier: Environment :: Console
Classifier: License :: OSI Approved :: GNU General Public License v3 (GPLv3)
Classifier: Programming Language :: Python
Classifier: Programming Language :: Python :: 2
Classifier: Programming Language :: Python :: 2.7
Classifier: Programming Language :: Python :: 3
Classifier: Programming Language :: Python :: 3.4
Classifier: Programming Language :: Python :: 3.5
Classifier: Programming Language :: Python :: 3.6
Classifier: Programming Language :: Python :: 3.7
Requires-Python: >=2.7, !=3.0.*, !=3.1.*, !=3.2.*, !=3.3.*
Requires-Dist: Click
